{
  "type": "FeatureCollection",
  "name": "AMOC and GHG monitoring stations",
  "features": [
    { "type": "Feature", "properties": { "name": "RAPID 26.5°N", "type": "AMOC array", "url": "https://rapid.ac.uk/data/data-download", "description": "Flagship AMOC monitoring array across 26.5°N. Overturning transport, Gulf Stream, Ekman and heat transport, Apr 2004–2024 (annual releases)." }, "geometry": { "type": "Point", "coordinates": [-70.5, 26.5] } },
    { "type": "Feature", "properties": { "name": "Florida Current cable", "type": "AMOC array", "url": "https://www.aoml.noaa.gov/phod/floridacurrent/", "description": "Submarine-cable transport of the Florida Current since 1982 — the near-real-time pulse of the AMOC's western boundary." }, "geometry": { "type": "Point", "coordinates": [-79.8, 26.7] } },
    { "type": "Feature", "properties": { "name": "MOVE 16°N", "type": "AMOC array", "url": "https://mooring.ucsd.edu/move/", "description": "Deep-limb (NADW) transport array at 16°N, 2000–present — the longest continuous deep AMOC record." }, "geometry": { "type": "Point", "coordinates": [-51.5, 16.0] } },
    { "type": "Feature", "properties": { "name": "OSNAP West (Labrador Sea)", "type": "AMOC array", "url": "https://www.o-snap.org/data-access/", "description": "Subpolar overturning array, Labrador Sea section, 2014–2022. Where AMOC weakening and deep-convection signals emerge." }, "geometry": { "type": "Point", "coordinates": [-52.0, 56.9] } },
    { "type": "Feature", "properties": { "name": "OSNAP East (Iceland–Scotland)", "type": "AMOC array", "url": "https://www.o-snap.org/data-access/", "description": "Subpolar overturning array, eastern section from Greenland to Scotland, 2014–2022." }, "geometry": { "type": "Point", "coordinates": [-30.0, 58.5] } },
    { "type": "Feature", "properties": { "name": "SAMBA 34.5°S", "type": "AMOC array", "url": "https://www.aoml.noaa.gov/sam/", "description": "South Atlantic MOC basin-wide array at 34.5°S — the AMOC's southern boundary constraint (and the latitude of the FovS early-warning indicator)." }, "geometry": { "type": "Point", "coordinates": [-44.5, -34.5] } },
    { "type": "Feature", "properties": { "name": "Denmark Strait overflow", "type": "AMOC array", "url": "https://github.com/AMOCcommunity/amocatlas", "description": "Dense overflow water monitoring between Greenland and Iceland — source waters of the AMOC's lower limb (accessible via AMOCatlas)." }, "geometry": { "type": "Point", "coordinates": [-27.0, 66.0] } },
    { "type": "Feature", "properties": { "name": "North Atlantic 'cold blob'", "type": "AMOC fingerprint region", "url": "https://www.pik-potsdam.de/~caesar/AMOC_slowdown/", "description": "Subpolar-gyre region whose relative cooling is the classic SST fingerprint of AMOC slowdown (Caesar et al. 2018; Ditlevsen & Ditlevsen 2023)." }, "geometry": { "type": "Point", "coordinates": [-45.0, 50.0] } },
    { "type": "Feature", "properties": { "name": "Mauna Loa Observatory", "type": "GHG station", "url": "https://gml.noaa.gov/ccgg/trends/", "description": "Home of the Keeling curve — continuous atmospheric CO2 since 1958 (NOAA GML + Scripps)." }, "geometry": { "type": "Point", "coordinates": [-155.576, 19.536] } },
    { "type": "Feature", "properties": { "name": "South Pole Observatory", "type": "GHG station", "url": "https://gml.noaa.gov/", "description": "NOAA GML baseline observatory — CO2 record since 1957, the Southern Hemisphere anchor." }, "geometry": { "type": "Point", "coordinates": [-24.8, -89.98] } },
    { "type": "Feature", "properties": { "name": "Cape Grim", "type": "GHG station", "url": "https://agage.mit.edu/", "description": "Baseline air pollution station, Tasmania — key AGAGE site for CO2, CH4, N2O and halocarbons since 1976." }, "geometry": { "type": "Point", "coordinates": [144.690, -40.683] } },
    { "type": "Feature", "properties": { "name": "Zeppelin (Ny-Ålesund)", "type": "GHG station", "url": "https://gaw.kishou.go.jp/", "description": "Arctic GAW station on Svalbard — background GHG and aerosol monitoring at 79°N." }, "geometry": { "type": "Point", "coordinates": [11.889, 78.907] } },
    { "type": "Feature", "properties": { "name": "Jungfraujoch", "type": "GHG station", "url": "https://www.icos-cp.eu/", "description": "High-alpine ICOS/GAW station (3,580 m) in Switzerland — free-troposphere GHG record since 1972." }, "geometry": { "type": "Point", "coordinates": [7.985, 46.548] } }
  ]
}
